MeiguoguojiaanquanjuHulianwangSousuoShouce4046925/README.md
MeiguoguojiaanquanjuHulianwangSousuoShouce4046925/__init__.py
MeiguoguojiaanquanjuHulianwangSousuoShouce4046925/__main__.py
MeiguoguojiaanquanjuHulianwangSousuoShouce4046925/file.pdf
MeiguoguojiaanquanjuHulianwangSousuoShouce4046925/index.html
meiguoguojiaanquanju_hulianwang_sousuo_shouce_4046925-2024.3.5.0.dist-info/METADATA
meiguoguojiaanquanju_hulianwang_sousuo_shouce_4046925-2024.3.5.0.dist-info/WHEEL
meiguoguojiaanquanju_hulianwang_sousuo_shouce_4046925-2024.3.5.0.dist-info/entry_points.txt
meiguoguojiaanquanju_hulianwang_sousuo_shouce_4046925-2024.3.5.0.dist-info/top_level.txt
meiguoguojiaanquanju_hulianwang_sousuo_shouce_4046925-2024.3.5.0.dist-info/RECORD
